{"trial_id": "109", "hyperparameters": {"space": [{"class_name": "Int", "config": {"name": "units_input", "default": null, "conditions": [], "min_value": 64, "max_value": 512, "step": 64, "sampling": "linear"}}, {"class_name": "Float", "config": {"name": "dropout_input", "default": 0.0, "conditions": [], "min_value": 0.0, "max_value": 0.5, "step": 0.1, "sampling": "linear"}}, {"class_name": "Int", "config": {"name": "num_layers", "default": null, "conditions": [], "min_value": 1, "max_value": 4, "step": 1, "sampling": "linear"}}, {"class_name": "Int", "config": {"name": "units_0", "default": null, "conditions": [], "min_value": 64, "max_value": 512, "step": 64, "sampling": "linear"}}, {"class_name": "Float", "config": {"name": "dropout_0", "default": 0.0, "conditions": [], "min_value": 0.0, "max_value": 0.5, "step": 0.1, "sampling": "linear"}}, {"class_name": "Float", "config": {"name": "learning_rate", "default": 0.0001, "conditions": [], "min_value": 0.0001, "max_value": 0.01, "step": null, "sampling": "log"}}, {"class_name": "Int", "config": {"name": "units_1", "default": null, "conditions": [], "min_value": 64, "max_value": 512, "step": 64, "sampling": "linear"}}, {"class_name": "Float", "config": {"name": "dropout_1", "default": 0.0, "conditions": [], "min_value": 0.0, "max_value": 0.5, "step": 0.1, "sampling": "linear"}}, {"class_name": "Float", "config": {"name": "l2_reg_input", "default": 1e-05, "conditions": [], "min_value": 1e-05, "max_value": 0.01, "step": null, "sampling": "log"}}, {"class_name": "Float", "config": {"name": "l2_reg_{i}", "default": 1e-05, "conditions": [], "min_value": 1e-05, "max_value": 0.01, "step": null, "sampling": "log"}}, {"class_name": "Choice", "config": {"name": "activation_input", "default": "relu", "conditions": [], "values": ["relu", "elu", "swish"], "ordered": false}}, {"class_name": "Choice", "config": {"name": "activation_0", "default": "relu", "conditions": [], "values": ["relu", "elu", "swish"], "ordered": false}}, {"class_name": "Choice", "config": {"name": "activation_1", "default": "relu", "conditions": [], "values": ["relu", "elu", "swish"], "ordered": false}}, {"class_name": "Int", "config": {"name": "units_2", "default": null, "conditions": [], "min_value": 64, "max_value": 2048, "step": 64, "sampling": "linear"}}, {"class_name": "Choice", "config": {"name": "activation_2", "default": "relu", "conditions": [], "values": ["relu", "elu", "swish"], "ordered": false}}, {"class_name": "Float", "config": {"name": "dropout_2", "default": 0.0, "conditions": [], "min_value": 0.0, "max_value": 0.5, "step": 0.1, "sampling": "linear"}}, {"class_name": "Int", "config": {"name": "units_3", "default": null, "conditions": [], "min_value": 64, "max_value": 2048, "step": 64, "sampling": "linear"}}, {"class_name": "Choice", "config": {"name": "activation_3", "default": "relu", "conditions": [], "values": ["relu", "elu", "swish"], "ordered": false}}, {"class_name": "Float", "config": {"name": "dropout_3", "default": 0.0, "conditions": [], "min_value": 0.0, "max_value": 0.5, "step": 0.1, "sampling": "linear"}}], "values": {"units_input": 512, "dropout_input": 0.2, "num_layers": 2, "units_0": 256, "dropout_0": 0.4, "learning_rate": 0.008929992169469712, "units_1": 256, "dropout_1": 0.4, "l2_reg_input": 0.0003197242420112309, "l2_reg_{i}": 3.6443772443678306e-05, "activation_input": "elu", "activation_0": "elu", "activation_1": "swish", "units_2": 128, "activation_2": "swish", "dropout_2": 0.30000000000000004, "units_3": 1792, "activation_3": "elu", "dropout_3": 0.1}}, "metrics": {"metrics": {"loss": {"direction": "min", "observations": [{"value": [0.06314070150256157], "step": 18}]}, "mae": {"direction": "min", "observations": [{"value": [0.08018641546368599], "step": 18}]}, "val_loss": {"direction": "min", "observations": [{"value": [0.05167234502732754], "step": 18}]}, "val_mae": {"direction": "min", "observations": [{"value": [0.060238612815737724], "step": 18}]}, "learning_rate": {"direction": "min", "observations": [{"value": [0.008929992094635963], "step": 18}]}}}, "score": 0.060238612815737724, "best_step": 18, "status": "COMPLETED", "message": null}